mlx_hyperbolic/__init__.py
mlx_hyperbolic/lorentz.py
mlx_hyperbolic/ops.py
mlx_hyperbolic-0.2.1.dist-info/licenses/LICENSE
mlx_hyperbolic-0.2.1.dist-info/METADATA
mlx_hyperbolic-0.2.1.dist-info/WHEEL
mlx_hyperbolic-0.2.1.dist-info/top_level.txt
mlx_hyperbolic-0.2.1.dist-info/RECORD
