Metadata-Version: 2.4
Name: mlx-hyperbolic
Version: 0.2.1
Summary: Fast hyperbolic geometry operations for MLX on Apple Silicon. Poincaré ball and Lorentz (hyperboloid) models with GPU acceleration.
Author-email: Nitin Borwankar <nitin@example.com>
License-Expression: MIT
Project-URL: Homepage, https://github.com/nborwankar/mlx-hyperbolic
Project-URL: Documentation, https://github.com/nborwankar/mlx-hyperbolic#readme
Project-URL: Repository, https://github.com/nborwankar/mlx-hyperbolic.git
Project-URL: Issues, https://github.com/nborwankar/mlx-hyperbolic/issues
Keywords: mlx,hyperbolic,embeddings,apple-silicon,metal,gpu,machine-learning,poincare,lorentz,hyperboloid,riemannian
Classifier: Development Status :: 4 - Beta
Classifier: Intended Audience :: Developers
Classifier: Intended Audience :: Science/Research
Classifier: Operating System :: MacOS :: MacOS X
Classifier: Programming Language :: Python :: 3
Classifier: Programming Language :: Python :: 3.11
Classifier: Programming Language :: Python :: 3.12
Classifier: Topic :: Scientific/Engineering :: Artificial Intelligence
Classifier: Topic :: Scientific/Engineering :: Mathematics
Requires-Python: >=3.11
License-File: LICENSE
Requires-Dist: mlx>=0.0.10
Requires-Dist: numpy>=1.24.0
Provides-Extra: dev
Requires-Dist: pytest>=7.0; extra == "dev"
Requires-Dist: pytest-benchmark>=4.0; extra == "dev"
Requires-Dist: black>=23.0; extra == "dev"
Requires-Dist: ruff>=0.1.0; extra == "dev"
Requires-Dist: mypy>=1.0; extra == "dev"
Provides-Extra: docs
Requires-Dist: sphinx>=6.0; extra == "docs"
Requires-Dist: sphinx-rtd-theme>=1.0; extra == "docs"
Dynamic: license-file
